xpboards/__init__.py
xpboards/dataset.py
xpboards/plan.py
xpboards/services.py
xpboards-0.1.3.dist-info/LICENSE.txt
xpboards-0.1.3.dist-info/METADATA
xpboards-0.1.3.dist-info/WHEEL
xpboards-0.1.3.dist-info/top_level.txt
xpboards-0.1.3.dist-info/RECORD
