Metadata-Version: 2.1
Name: xpboards
Version: 0.1.3
Summary: A python util for xpboards
Home-page: UNKNOWN
Author: Douglas Eloy
License: MIT
Platform: UNKNOWN
Requires-Dist: requests
